mcp_mysql/__init__.py
mcp_mysql/database.py
mcp_mysql/server.py
mcp_postgresql/__init__.py
mcp_postgresql/database.py
mcp_postgresql/server.py
da2_mcp_multi_db-0.1.1.dist-info/METADATA
da2_mcp_multi_db-0.1.1.dist-info/WHEEL
da2_mcp_multi_db-0.1.1.dist-info/entry_points.txt
da2_mcp_multi_db-0.1.1.dist-info/licenses/LICENSE
da2_mcp_multi_db-0.1.1.dist-info/RECORD
