Metadata-Version: 2.4
Name: da2-mcp-multi-db
Version: 0.1.1
Summary: A Multi-Database MCP Server - enables AI assistants to query and explore PostgreSQL and MySQL databases
Project-URL: Homepage, https://da2.35g.tw
Author-email: Danny <danny@35g.tw>, DA2 Studio <contact@35g.tw>
License: MIT
License-File: LICENSE
Keywords: ai,database,llm,mariadb,mcp,mysql,postgresql
Requires-Python: >=3.10
Requires-Dist: mcp[cli]>=1.0.0
Requires-Dist: mysql-connector-python>=8.0.0
Requires-Dist: psycopg2-binary>=2.9.0
Requires-Dist: python-dotenv>=1.0.0
